{
  "RestaurantId": 1,
  "Name": "Restaurant1",
  "Address": "https://localhost:7299/order",
  "Menu": [
    {
      "Id": 1,
      "Name": "Pizza",
      "PreparationTime": 1,
      "Complexity": 2
    },
    {
      "Id": 2,
      "Name": "Salad",
      "PreparationTime": 10,
      "Complexity": 1
    },
    {
      "Id": 3,
      "Name": "Zeama",
      "PreparationTime": 7,
      "Complexity": 1
    },
    {
      "Id": 4,
      "Name": "Scallop Sashimi with Meyer Lemon Confit",
      "PreparationTime": 32,
      "Complexity": 3
    },
    {
      "Id": 5,
      "Name": "Island Duck with Mulberry Mustard",
      "PreparationTime": 35,
      "Complexity": 3
    },
    {
      "Id": 6,
      "Name": "Waffles",
      "PreparationTime": 10,
      "Complexity": 1
    },
    {
      "Id": 7,
      "Name": "Aubergine",
      "PreparationTime": 20,
      "Complexity": 2
    },
    {
      "Id": 8,
      "Name": "Lasagna",
      "PreparationTime": 30,
      "Complexity": 2
    },
    {
      "Id": 9,
      "Name": "Burger",
      "PreparationTime": 15,
      "Complexity": 1
    },
    {
      "Id": 10,
      "Name": "Gyros",
      "PreparationTime": 15,
      "Complexity": 1
    },
    {
      "Id": 11,
      "Name": "Kebab",
      "PreparationTime": 15,
      "Complexity": 1
    },
    {
      "Id": 12,
      "Name": "UnagiMaki",
      "PreparationTime": 20,
      "Complexity": 2
    },
    {
      "Id": 13,
      "Name": "TobaccoChicken",
      "PreparationTime": 30,
      "Complexity": 2
    }
  ]
}